README.md
setup.py
wave_checker/__init__.py
wave_checker/main.py
wave_checker.egg-info/PKG-INFO
wave_checker.egg-info/SOURCES.txt
wave_checker.egg-info/dependency_links.txt
wave_checker.egg-info/requires.txt
wave_checker.egg-info/top_level.txt
wave_checker/analysis/__init__.py
wave_checker/analysis/analysis.py
wave_checker/analysis/best_moments.py
wave_checker/analysis/reader.py
wave_checker/data_vis/__init__.py
wave_checker/data_vis/plot_best_moments.py
wave_checker/scrape_url/__init__.py
wave_checker/scrape_url/scrape.py
wave_checker/scrape_url/scrape_content.py
wave_checker/scrape_url/scrape_titles.py