Metadata-Version: 1.1
Name: wave-checker
Version: 1.0.0
Summary: Easy way to find the best waves by analyzing windguru
Home-page: https://github.com/cristinafareizaga/wave_checker.git
Author: Cristina Areizaga
Author-email: cristinafareizaga@gmail.com
License: UNKNOWN
Platform: UNKNOWN
Classifier: Programming Language :: Python :: 3
Classifier: License :: OSI Approved :: MIT License
